input_paste/__init__.py
input_paste/input_paste.css
input_paste/input_paste.py
input_paste-0.1.2.dist-info/DESCRIPTION.rst
input_paste-0.1.2.dist-info/METADATA
input_paste-0.1.2.dist-info/RECORD
input_paste-0.1.2.dist-info/WHEEL
input_paste-0.1.2.dist-info/entry_points.txt
input_paste-0.1.2.dist-info/metadata.json
input_paste-0.1.2.dist-info/top_level.txt
