Metadata-Version: 2.0
Name: input-paste
Version: 0.1.2
Summary: Linux上利用剪貼簿協助打中文的工具
Home-page: https://github.com/RPing/input-paste
Author: Stephen Chen
Author-email: g1222888@gmail.com
License: MIT
Keywords: chinese input helper paste clipboard imfix
Platform: UNKNOWN
Classifier: Operating System :: Unix
Classifier: Environment :: X11 Applications
Classifier: License :: OSI Approved :: MIT License
Classifier: Programming Language :: Python
Classifier: Programming Language :: Python :: 2
Classifier: Programming Language :: Python :: 3
Classifier: Topic :: Utilities
